management/__init__.py
migrations/__init__.py
hani_django_maker-1.0.dist-info/METADATA
hani_django_maker-1.0.dist-info/WHEEL
hani_django_maker-1.0.dist-info/top_level.txt
hani_django_maker-1.0.dist-info/RECORD
